LICENSE
README.md
setup.py
geojson2osm/__init__.py
geojson2osm/geojson2osm.py
geojson2osm.egg-info/PKG-INFO
geojson2osm.egg-info/SOURCES.txt
geojson2osm.egg-info/dependency_links.txt
geojson2osm.egg-info/requires.txt
geojson2osm.egg-info/top_level.txt
tests/__init__.py
tests/test_geojson2osm.py