Metadata-Version: 2.1
Name: geojson2osm
Version: 0.0.1
Summary: A Python package to convert GeoJSON data to OSM XML format
Home-page: https://github.com/kshitijrajsharma/geojson2osm
Author: Kshitijraj Sharma
Author-email: skshitizraj@gmail.com
License: MIT
Classifier: Development Status :: 3 - Alpha
Classifier: License :: OSI Approved :: MIT License
Classifier: Programming Language :: Python :: 3
Classifier: Programming Language :: Python :: 3.6
Classifier: Programming Language :: Python :: 3.7
Classifier: Programming Language :: Python :: 3.8
Classifier: Programming Language :: Python :: 3.9
License-File: LICENSE
